trainner/__init__.py
trainner/databatch.py
trainner/train.py
trainner-0.0.5.dist-info/METADATA
trainner-0.0.5.dist-info/WHEEL
trainner-0.0.5.dist-info/top_level.txt
trainner-0.0.5.dist-info/RECORD
