Metadata-Version: 2.1
Name: trainner
Version: 0.0.5
Summary: A small package for trainning in deep learning
Home-page: UNKNOWN
Author: haijie
Author-email: 963493140@qq.com
License: UNKNOWN
Platform: UNKNOWN
Classifier: Programming Language :: Python :: 3
Classifier: License :: OSI Approved :: MIT License
Classifier: Operating System :: OS Independent
Requires-Dist: torch
Requires-Dist: numpy
Requires-Dist: matplotlib
